ais_gloss/__init__.py
ais_gloss/auto_trainer.py
ais_gloss/gloss_recommender.py
ais_gloss/visualization.py
ais_gloss/models/__init__.py
ais_gloss/models/pytorch_models.py
ais_gloss/models/sklearn_models.py
ais_gloss/utils/__init__.py
ais_gloss/utils/logger.py
ais_gloss/utils/metrics.py
ais_gloss-0.1.0.dist-info/LICENSE
ais_gloss-0.1.0.dist-info/METADATA
ais_gloss-0.1.0.dist-info/WHEEL
ais_gloss-0.1.0.dist-info/top_level.txt
ais_gloss-0.1.0.dist-info/RECORD
