Metadata-Version: 2.1
Name: ais_gloss
Version: 0.1.0
Summary: AI-Scientist GLOSS Recommendation System
Home-page: https://github.com/zbc0315/ais_gloss
Author: Zhang, Baicheng
Author-email: "Zhang, Baicheng" <zbc@ustc.edu.cn>
License: MIT
Project-URL: Homepage, https://github.com/zbc0315/ais_gloss
Project-URL: Documentation, https://zbc0315.github.io/ais_gloss/
Project-URL: Repository, https://github.com/zbc0315/ais_gloss
Project-URL: Bug Tracker, https://github.com/zbc0315/ais_gloss/issues
Keywords: AI-Scientist,machine learning,automl,optimization,gloss
Classifier: Development Status :: 3 - Alpha
Classifier: Intended Audience :: Science/Research
Classifier: License :: OSI Approved :: MIT License
Classifier: Programming Language :: Python :: 3
Classifier: Programming Language :: Python :: 3.8
Classifier: Programming Language :: Python :: 3.9
Classifier: Programming Language :: Python :: 3.10
Classifier: Programming Language :: Python :: 3.11
Requires-Python: >=3.8
License-File: LICENSE
Requires-Dist: numpy>=1.21.0
Requires-Dist: pandas>=1.3.0
Requires-Dist: scikit-learn>=1.0.0
Requires-Dist: torch>=1.10.0
Requires-Dist: matplotlib>=3.4.0
Requires-Dist: seaborn>=0.11.0
Requires-Dist: bayesian-optimization>=1.2.0
Requires-Dist: joblib>=1.1.0
Requires-Dist: tqdm>=4.62.0
Provides-Extra: dev
Requires-Dist: pytest>=6.0; extra == "dev"
Requires-Dist: pytest-cov>=2.0; extra == "dev"
Requires-Dist: black>=21.0; extra == "dev"
Requires-Dist: flake8>=3.9; extra == "dev"
Provides-Extra: docs
Requires-Dist: mkdocs>=1.4.0; extra == "docs"
Requires-Dist: mkdocs-material>=8.0.0; extra == "docs"
